SiteToSheet/__init__.py
SiteToSheet/config.py
SiteToSheet/main.py
SiteToSheet/api_clients/__init__.py
SiteToSheet/api_clients/google_maps_client.py
SiteToSheet/api_clients/google_sheets_client.py
SiteToSheet/scrapers/__init__.py
SiteToSheet/scrapers/web_scraping.py
SiteToSheet/utils/__init__.py
SiteToSheet/utils/shelf_functions.py
SiteToSheet/utils/tube_stops.txt
SiteToSheet-1.0.0.dist-info/LICENSE
SiteToSheet-1.0.0.dist-info/METADATA
SiteToSheet-1.0.0.dist-info/WHEEL
SiteToSheet-1.0.0.dist-info/entry_points.txt
SiteToSheet-1.0.0.dist-info/top_level.txt
SiteToSheet-1.0.0.dist-info/RECORD
