Metadata-Version: 2.1
Name: SiteToSheet
Version: 1.0.0
Summary: A tool to scrape websites and update Google Sheets
Author-email: Jonathan <jontyshaw@btinternet.com>
License: MIT
Project-URL: homepage, https://github.com/jonty/SiteToSheet
Requires-Python: >=3.7
License-File: LICENSE
Requires-Dist: beautifulsoup4>=4.12.3
Requires-Dist: googlemaps>=4.10.0
Requires-Dist: gspread>=6.1.2
Requires-Dist: numpy>=1.26.4
Requires-Dist: pandas>=2.2.2
Requires-Dist: protobuf>=5.27.3
Requires-Dist: python-dotenv>=1.0.1
Requires-Dist: ratelimit>=2.2.1
Requires-Dist: requests>=2.32.3
Requires-Dist: setuptools>=72.1.0
Requires-Dist: spacy>=3.7.5
Provides-Extra: dev
Requires-Dist: twine; extra == "dev"
